spherical/__init__.py
spherical/__version__.py
spherical/multiplication.py
spherical/wigner.py
spherical/grid/__init__.py
spherical/grid/algebra.py
spherical/grid/ufuncs.py
spherical/grid/utilities.py
spherical/modes/__init__.py
spherical/modes/algebra.py
spherical/modes/derivatives.py
spherical/modes/rotate.py
spherical/modes/ufuncs.py
spherical/modes/utilities.py
spherical/recursions/__init__.py
spherical/recursions/complex_powers.py
spherical/recursions/wigner3j.py
spherical/recursions/wignerH.py
spherical/utilities/__init__.py
spherical/utilities/indexing.py
spherical/utilities/mode_conversions.py
spherical/utilities/operators.py
spherical-1.0.18.dist-info/METADATA
spherical-1.0.18.dist-info/WHEEL
spherical-1.0.18.dist-info/licenses/LICENSE
spherical-1.0.18.dist-info/RECORD
