Metadata-Version: 2.4
Name: spherical
Version: 1.0.18
Summary: Evaluate and transform D matrices, 3-j symbols, and (scalar or spin-weighted) spherical harmonics
Project-URL: Homepage, https://github.com/moble/spherical
Project-URL: Documentation, https://spherical.readthedocs.io/
Author-email: Michael Boyle <michael.oliver.boyle@gmail.com>
License: The MIT License (MIT)
License-File: LICENSE
Classifier: Development Status :: 5 - Production/Stable
Classifier: Intended Audience :: Science/Research
Classifier: License :: OSI Approved :: MIT License
Classifier: Operating System :: OS Independent
Classifier: Programming Language :: Python :: 3
Classifier: Topic :: Scientific/Engineering :: Astronomy
Classifier: Topic :: Scientific/Engineering :: Physics
Requires-Python: >=3.10
Requires-Dist: numba>=0.55; implementation_name == 'cpython'
Requires-Dist: numpy>=1.20
Requires-Dist: quaternionic>=1.0
Requires-Dist: scipy>=1.5
Requires-Dist: spinsfast>=104.2020.8; sys_platform != 'win32'
Provides-Extra: docs
Requires-Dist: mkdocs; extra == 'docs'
Requires-Dist: mktheapidocs; extra == 'docs'
Requires-Dist: pymdown-extensions; extra == 'docs'
